README.rst
gitopen.py
setup.py
Gitopen.egg-info/PKG-INFO
Gitopen.egg-info/SOURCES.txt
Gitopen.egg-info/dependency_links.txt
Gitopen.egg-info/entry_points.txt
Gitopen.egg-info/pbr.json
Gitopen.egg-info/requires.txt
Gitopen.egg-info/top_level.txt