Metadata-Version: 1.1
Name: Gitopen
Version: 1.2.1
Summary: Open your git-remote url in your browser
Home-page: https://github.com/guinslym/gitopen
Author: Guinslym
Author-email: guinslym@gmail.com
License: GNU GPLv2
Keywords: git repo repoitory gitbucket
Platform: UNKNOWN
Classifier: Development Status :: 5 - Production/Stable
Classifier: Intended Audience :: Developers
Classifier: License :: OSI Approved :: GNU General Public License v3 or later (GPLv3+)
Classifier: Programming Language :: Python :: 2.6
Classifier: Programming Language :: Python :: 2.7
Classifier: Programming Language :: Python :: 3.2
Classifier: Programming Language :: Python :: 3.3
Classifier: Programming Language :: Python :: 3.4
